anafit/__init__.py
anafit/ana_icon.png
anafit/ana_icon.svg
anafit/anafit.py
anafit/customFitDialog.py
anafit/customFitDialog.ui
anafit/ui.py
anafit/utilities.py
anafit-0.1.6.dist-info/METADATA
anafit-0.1.6.dist-info/RECORD
anafit-0.1.6.dist-info/WHEEL
anafit-0.1.6.dist-info/top_level.txt
