Metadata-Version: 2.1
Name: anafit
Version: 0.1.6
Summary: A toolbox providing interactive fitting tools for matplotlib
Home-page: https://gitlab.com/xamcosta/Anafit
Author: Maxime Costalonga
Author-email: maxime.costalonga@gmail.com
License: UNKNOWN
Keywords: matplotlib fit
Platform: UNKNOWN
Classifier: Programming Language :: Python :: 3.7
Classifier: Topic :: Scientific/Engineering
Requires-Dist: matplotlib
Requires-Dist: numpy
Requires-Dist: scipy
